odoo8_addon_l10n_pt_vat-8.0.0.0.3.99.dev3-py2.7-nspkg.pth
odoo8_addon_l10n_pt_vat-8.0.0.0.3.99.dev3.dist-info/DESCRIPTION.rst
odoo8_addon_l10n_pt_vat-8.0.0.0.3.99.dev3.dist-info/METADATA
odoo8_addon_l10n_pt_vat-8.0.0.0.3.99.dev3.dist-info/RECORD
odoo8_addon_l10n_pt_vat-8.0.0.0.3.99.dev3.dist-info/WHEEL
odoo8_addon_l10n_pt_vat-8.0.0.0.3.99.dev3.dist-info/metadata.json
odoo8_addon_l10n_pt_vat-8.0.0.0.3.99.dev3.dist-info/namespace_packages.txt
odoo8_addon_l10n_pt_vat-8.0.0.0.3.99.dev3.dist-info/top_level.txt
odoo_addons/l10n_pt_vat/README.rst
odoo_addons/l10n_pt_vat/__init__.py
odoo_addons/l10n_pt_vat/__openerp__.py
odoo_addons/l10n_pt_vat/data/vat_adjustment_norm.xml
odoo_addons/l10n_pt_vat/i18n/pt.po
odoo_addons/l10n_pt_vat/models/__init__.py
odoo_addons/l10n_pt_vat/models/account_invoice.py
odoo_addons/l10n_pt_vat/models/vat_adjustment_norm.py
odoo_addons/l10n_pt_vat/security/ir.model.access.csv
odoo_addons/l10n_pt_vat/static/description/icon.png
odoo_addons/l10n_pt_vat/views/account_invoice_view.xml
odoo_addons/l10n_pt_vat/views/vat_adjustment_norm_view.xml
